[
  {
    "full_name": "moonlight-stream/moonlight-android",
    "stargazers_count": 3443,
    "open_issues_count": 222,
    "forks_count": 526
  },
  {
    "full_name": "LizardByte/Sunshine",
    "stargazers_count": 14973,
    "open_issues_count": 89,
    "forks_count": 721
  },
  {
    "full_name": "ethanlynn/calcium",
    "stargazers_count": 40,
    "open_issues_count": 0,
    "forks_count": 2
  },
  {
    "full_name": "huggingface/transformers",
    "stargazers_count": 128067,
    "open_issues_count": 1132,
    "forks_count": 25399
  },
  {
    "full_name": "elevenlabs/elevenlabs-python",
    "stargazers_count": 1956,
    "open_issues_count": 31,
    "forks_count": 222
  },
  {
    "full_name": "amix/vimrc",
    "stargazers_count": 30313,
    "open_issues_count": 2,
    "forks_count": 7255
  },
  {
    "full_name": "rust-lang/rust",
    "stargazers_count": 94521,
    "open_issues_count": 10052,
    "forks_count": 12181
  },
  {
    "full_name": "near/borsh",
    "stargazers_count": 467,
    "open_issues_count": 39,
    "forks_count": 39
  },
  {
    "full_name": "coral-xyz/backpack",
    "stargazers_count": 1250,
    "open_issues_count": 490,
    "forks_count": 754
  },
  {
    "full_name": "signalapp/Signal-Android",
    "stargazers_count": 25127,
    "open_issues_count": 377,
    "forks_count": 6046
  },
  {
    "full_name": "Saganize/Solwave-kt",
    "stargazers_count": 7,
    "open_issues_count": 0,
    "forks_count": 0
  },
  {
    "full_name": "prasanthrangan/hyprdots",
    "stargazers_count": 5478,
    "open_issues_count": 112,
    "forks_count": 668
  },
  {
    "full_name": "koodo-reader/koodo-reader",
    "stargazers_count": 16739,
    "open_issues_count": 427,
    "forks_count": 1289
  },
  {
    "full_name": "facebook/docusaurus",
    "stargazers_count": 53898,
    "open_issues_count": 325,
    "forks_count": 8072
  },
  {
    "full_name": "bumptech/glide",
    "stargazers_count": 34445,
    "open_issues_count": 527,
    "forks_count": 6099
  },
  {
    "full_name": "anamansari062/GM",
    "stargazers_count": 7,
    "open_issues_count": 0,
    "forks_count": 0
  },
  {
    "full_name": "altstoreio/AltStore",
    "stargazers_count": 11299,
    "open_issues_count": 479,
    "forks_count": 858
  },
  {
    "full_name": "ish-app/ish",
    "stargazers_count": 16290,
    "open_issues_count": 594,
    "forks_count": 852
  },
  {
    "full_name": "maunium/dontasktoask.com",
    "stargazers_count": 406,
    "open_issues_count": 12,
    "forks_count": 90
  },
  {
    "full_name": "darlinghq/darling",
    "stargazers_count": 11183,
    "open_issues_count": 293,
    "forks_count": 426
  },
  {
    "full_name": "exelban/stats",
    "stargazers_count": 22989,
    "open_issues_count": 18,
    "forks_count": 770
  },
  {
    "full_name": "cdhiraj40/mobile-dapp-scaffold",
    "stargazers_count": 11,
    "open_issues_count": 3,
    "forks_count": 5
  },
  {
    "full_name": "calcom/cal.com",
    "stargazers_count": 29607,
    "open_issues_count": 839,
    "forks_count": 6915
  },
  {
    "full_name": "solana-labs/dapp-scaffold",
    "stargazers_count": 1698,
    "open_issues_count": 19,
    "forks_count": 953
  },
  {
    "full_name": "nektos/act",
    "stargazers_count": 51748,
    "open_issues_count": 207,
    "forks_count": 1301
  },
  {
    "full_name": "vitest-dev/vitest",
    "stargazers_count": 12130,
    "open_issues_count": 305,
    "forks_count": 1065
  },
  {
    "full_name": "vercel/turbo",
    "stargazers_count": 25427,
    "open_issues_count": 186,
    "forks_count": 1721
  },
  {
    "full_name": "creativedrewy/NATIV",
    "stargazers_count": 25,
    "open_issues_count": 0,
    "forks_count": 7
  },
  {
    "full_name": "ironforge-cloud/soldev-ui",
    "stargazers_count": 29,
    "open_issues_count": 13,
    "forks_count": 27
  },
  {
    "full_name": "metaplex-foundation/SolanaKT",
    "stargazers_count": 63,
    "open_issues_count": 16,
    "forks_count": 32
  }
]