[
  {
    "full_name": "ethanlynn/calcium",
    "stargazers_count": 24,
    "open_issues_count": 0,
    "forks_count": 1
  },
  {
    "full_name": "huggingface/transformers",
    "stargazers_count": 119087,
    "open_issues_count": 940,
    "forks_count": 23839
  },
  {
    "full_name": "elevenlabs/elevenlabs-python",
    "stargazers_count": 1527,
    "open_issues_count": 54,
    "forks_count": 172
  },
  {
    "full_name": "amix/vimrc",
    "stargazers_count": 29817,
    "open_issues_count": 0,
    "forks_count": 7262
  },
  {
    "full_name": "rust-lang/rust",
    "stargazers_count": 89152,
    "open_issues_count": 9715,
    "forks_count": 11936
  },
  {
    "full_name": "near/borsh",
    "stargazers_count": 427,
    "open_issues_count": 38,
    "forks_count": 39
  },
  {
    "full_name": "coral-xyz/backpack",
    "stargazers_count": 1030,
    "open_issues_count": 455,
    "forks_count": 652
  },
  {
    "full_name": "signalapp/Signal-Android",
    "stargazers_count": 24538,
    "open_issues_count": 313,
    "forks_count": 6023
  },
  {
    "full_name": "Saganize/Solwave-kt",
    "stargazers_count": 6,
    "open_issues_count": 0,
    "forks_count": 0
  },
  {
    "full_name": "prasanthrangan/hyprdots",
    "stargazers_count": 3076,
    "open_issues_count": 95,
    "forks_count": 407
  },
  {
    "full_name": "koodo-reader/koodo-reader",
    "stargazers_count": 14306,
    "open_issues_count": 327,
    "forks_count": 1120
  },
  {
    "full_name": "facebook/docusaurus",
    "stargazers_count": 50876,
    "open_issues_count": 322,
    "forks_count": 7817
  },
  {
    "full_name": "bumptech/glide",
    "stargazers_count": 34167,
    "open_issues_count": 489,
    "forks_count": 6142
  },
  {
    "full_name": "anamansari062/GM",
    "stargazers_count": 7,
    "open_issues_count": 0,
    "forks_count": 0
  },
  {
    "full_name": "altstoreio/AltStore",
    "stargazers_count": 10263,
    "open_issues_count": 400,
    "forks_count": 798
  },
  {
    "full_name": "ish-app/ish",
    "stargazers_count": 15450,
    "open_issues_count": 563,
    "forks_count": 842
  },
  {
    "full_name": "maunium/dontasktoask.com",
    "stargazers_count": 385,
    "open_issues_count": 7,
    "forks_count": 90
  },
  {
    "full_name": "darlinghq/darling",
    "stargazers_count": 10785,
    "open_issues_count": 273,
    "forks_count": 423
  },
  {
    "full_name": "exelban/stats",
    "stargazers_count": 20186,
    "open_issues_count": 13,
    "forks_count": 681
  },
  {
    "full_name": "cdhiraj40/mobile-dapp-scaffold",
    "stargazers_count": 11,
    "open_issues_count": 3,
    "forks_count": 5
  },
  {
    "full_name": "calcom/cal.com",
    "stargazers_count": 26697,
    "open_issues_count": 640,
    "forks_count": 5922
  },
  {
    "full_name": "solana-labs/dapp-scaffold",
    "stargazers_count": 1585,
    "open_issues_count": 13,
    "forks_count": 847
  },
  {
    "full_name": "nektos/act",
    "stargazers_count": 46812,
    "open_issues_count": 202,
    "forks_count": 1176
  },
  {
    "full_name": "vitest-dev/vitest",
    "stargazers_count": 11132,
    "open_issues_count": 351,
    "forks_count": 968
  },
  {
    "full_name": "vercel/turbo",
    "stargazers_count": 24002,
    "open_issues_count": 406,
    "forks_count": 1639
  },
  {
    "full_name": "creativedrewy/NATIV",
    "stargazers_count": 25,
    "open_issues_count": 0,
    "forks_count": 7
  },
  {
    "full_name": "ironforge-cloud/soldev-ui",
    "stargazers_count": 12,
    "open_issues_count": 5,
    "forks_count": 21
  },
  {
    "full_name": "metaplex-foundation/SolanaKT",
    "stargazers_count": 58,
    "open_issues_count": 16,
    "forks_count": 28
  },
  {
    "full_name": "solana-mobile/mobile-wallet-adapter",
    "stargazers_count": 184,
    "open_issues_count": 36,
    "forks_count": 78
  },
  {
    "full_name": "zidoro/pomatez",
    "stargazers_count": 3482,
    "open_issues_count": 154,
    "forks_count": 147
  }
]