[
  {
    "full_name": "espanso/espanso",
    "stargazers_count": 10265,
    "open_issues_count": 395,
    "forks_count": 282
  },
  {
    "full_name": "iamvon/zk-compression-nextjs-actions",
    "stargazers_count": 2,
    "open_issues_count": 0,
    "forks_count": 0
  },
  {
    "full_name": "visgl/deck.gl",
    "stargazers_count": 12379,
    "open_issues_count": 367,
    "forks_count": 2097
  },
  {
    "full_name": "moonlight-stream/moonlight-android",
    "stargazers_count": 4492,
    "open_issues_count": 289,
    "forks_count": 716
  },
  {
    "full_name": "LizardByte/Sunshine",
    "stargazers_count": 21429,
    "open_issues_count": 105,
    "forks_count": 1021
  },
  {
    "full_name": "ethanlynn/calcium",
    "stargazers_count": 45,
    "open_issues_count": 0,
    "forks_count": 3
  },
  {
    "full_name": "huggingface/transformers",
    "stargazers_count": 137234,
    "open_issues_count": 1543,
    "forks_count": 27473
  },
  {
    "full_name": "elevenlabs/elevenlabs-python",
    "stargazers_count": 2322,
    "open_issues_count": 63,
    "forks_count": 273
  },
  {
    "full_name": "amix/vimrc",
    "stargazers_count": 30913,
    "open_issues_count": 10,
    "forks_count": 7309
  },
  {
    "full_name": "rust-lang/rust",
    "stargazers_count": 100279,
    "open_issues_count": 10574,
    "forks_count": 12952
  },
  {
    "full_name": "near/borsh",
    "stargazers_count": 526,
    "open_issues_count": 40,
    "forks_count": 41
  },
  {
    "full_name": "coral-xyz/backpack",
    "stargazers_count": 1415,
    "open_issues_count": 497,
    "forks_count": 839
  },
  {
    "full_name": "signalapp/Signal-Android",
    "stargazers_count": 25863,
    "open_issues_count": 475,
    "forks_count": 6214
  },
  {
    "full_name": "Saganize/Solwave-kt",
    "stargazers_count": 8,
    "open_issues_count": 0,
    "forks_count": 0
  },
  {
    "full_name": "prasanthrangan/hyprdots",
    "stargazers_count": 8173,
    "open_issues_count": 84,
    "forks_count": 930
  },
  {
    "full_name": "koodo-reader/koodo-reader",
    "stargazers_count": 20288,
    "open_issues_count": 522,
    "forks_count": 1573
  },
  {
    "full_name": "facebook/docusaurus",
    "stargazers_count": 57521,
    "open_issues_count": 338,
    "forks_count": 8684
  },
  {
    "full_name": "bumptech/glide",
    "stargazers_count": 34740,
    "open_issues_count": 553,
    "forks_count": 6130
  },
  {
    "full_name": "anamansari062/GM",
    "stargazers_count": 7,
    "open_issues_count": 0,
    "forks_count": 0
  },
  {
    "full_name": "altstoreio/AltStore",
    "stargazers_count": 11977,
    "open_issues_count": 525,
    "forks_count": 925
  },
  {
    "full_name": "ish-app/ish",
    "stargazers_count": 17420,
    "open_issues_count": 632,
    "forks_count": 937
  },
  {
    "full_name": "maunium/dontasktoask.com",
    "stargazers_count": 438,
    "open_issues_count": 17,
    "forks_count": 98
  },
  {
    "full_name": "darlinghq/darling",
    "stargazers_count": 11638,
    "open_issues_count": 304,
    "forks_count": 451
  },
  {
    "full_name": "exelban/stats",
    "stargazers_count": 27105,
    "open_issues_count": 20,
    "forks_count": 896
  },
  {
    "full_name": "cdhiraj40/mobile-dapp-scaffold",
    "stargazers_count": 11,
    "open_issues_count": 3,
    "forks_count": 5
  },
  {
    "full_name": "calcom/cal.com",
    "stargazers_count": 33271,
    "open_issues_count": 957,
    "forks_count": 8330
  },
  {
    "full_name": "solana-labs/dapp-scaffold",
    "stargazers_count": 1790,
    "open_issues_count": 21,
    "forks_count": 1010
  },
  {
    "full_name": "nektos/act",
    "stargazers_count": 56610,
    "open_issues_count": 211,
    "forks_count": 1433
  },
  {
    "full_name": "vitest-dev/vitest",
    "stargazers_count": 13505,
    "open_issues_count": 336,
    "forks_count": 1227
  },
  {
    "full_name": "vercel/turborepo",
    "stargazers_count": 26747,
    "open_issues_count": 175,
    "forks_count": 1868
  }
]